[
  {
    "page_id": "60cdd278d485426860b64033fef4e0e61db267f0",
    "job_id": "22b02a9a-e239-4e6f-9519-a7f6b6bdd8a0",
    "url": "https://resmigazete.gov.tr/",
    "domain": "resmigazete.gov.tr",
    "depth": 0,
    "text_path": "data/resmigazete_gov_tr/pages/text/60cdd278d485426860b64033fef4e0e61db267f0.txt",
    "content_type": "text/html; charset=utf-8",
    "discovered_links": [
      "https://resmigazete.gov.tr/",
      "https://resmigazete.gov.tr/fihrist?tarih=2025-12-31&mukerrer=6",
      "https://resmigazete.gov.tr/08.01.2026",
      "https://www.resmigazete.gov.tr/eskiler/2026/01/20260109-1.htm",
      "https://www.resmigazete.gov.tr/eskiler/2026/01/20260109-2.htm",
      "https://www.resmigazete.gov.tr/eskiler/2026/01/20260109-3.htm",
      "https://www.resmigazete.gov.tr/eskiler/2026/01/20260109-4.htm",
      "https://www.resmigazete.gov.tr/eskiler/2026/01/20260109-5.htm",
      "https://www.resmigazete.gov.tr/ilanlar/eskiilanlar/2026/01/20260109-2.htm",
      "https://www.resmigazete.gov.tr/ilanlar/eskiilanlar/2026/01/20260109-3.htm",
      "https://www.resmigazete.gov.tr/ilanlar/eskiilanlar/2026/01/20260109-4.htm",
      "https://www.resmigazete.gov.tr/ilanlar/eskiilanlar/2026/01/20260109-5.htm"
    ],
    "discovered_files": [
      "https://www.resmigazete.gov.tr/eskiler/2026/01/20260109.pdf",
      "https://www.resmigazete.gov.tr/eskiler/2026/01/20260109-6.pdf",
      "https://www.resmigazete.gov.tr/eskiler/2026/01/20260109-7.pdf"
    ],
    "content_hash": "61f7d67a03e57a3acc059f3139a296866cd45cfe5f43cd75d92c7561e0dc499d",
    "text_len": 41802,
    "agent_id": "bc001",
    "project_id": 6
  },
  {
    "page_id": "2a4f3c08a897a97b0adf27807858c4cbbf06eac9",
    "job_id": "22b02a9a-e239-4e6f-9519-a7f6b6bdd8a0",
    "url": "https://resmigazete.gov.tr/fihrist?tarih=2025-12-31&mukerrer=6",
    "domain": "resmigazete.gov.tr",
    "depth": 1,
    "text_path": "data/resmigazete_gov_tr/pages/text/2a4f3c08a897a97b0adf27807858c4cbbf06eac9.txt",
    "content_type": "text/html; charset=utf-8",
    "discovered_links": [
      "https://resmigazete.gov.tr/",
      "https://resmigazete.gov.tr/fihrist?tarih=2025-12-31&mukerrer=5",
      "https://www.resmigazete.gov.tr/ilanlar/eskiilanlar/2025/12/20251231%20M6-4.htm",
      "https://resmigazete.gov.tr/fihrist?tarih=2025-12-31&mukerrer=6"
    ],
    "discovered_files": [
      "https://www.resmigazete.gov.tr/eskiler/2025/12/20251231M6.pdf",
      "https://www.resmigazete.gov.tr/eskiler/2025/12/20251231M6-1.pdf",
      "https://www.resmigazete.gov.tr/eskiler/2025/12/20251231M6-2.pdf",
      "https://www.resmigazete.gov.tr/eskiler/2025/12/20251231M6-3.pdf",
      "https://www.resmigazete.gov.tr/eskiler/2025/12/20251231M6-4.pdf",
      "https://www.resmigazete.gov.tr/eskiler/2025/12/20251231M6-5.pdf",
      "https://www.resmigazete.gov.tr/eskiler/2025/12/20251231M6-6.pdf",
      "https://www.resmigazete.gov.tr/eskiler/2025/12/20251231M6-7.pdf",
      "https://www.resmigazete.gov.tr/eskiler/2025/12/20251231M6-8.pdf",
      "https://www.resmigazete.gov.tr/eskiler/2025/12/20251231M6-9.pdf",
      "https://www.resmigazete.gov.tr/eskiler/2025/12/20251231M6-10.pdf",
      "https://www.resmigazete.gov.tr/eskiler/2025/12/20251231M6-11.pdf",
      "https://www.resmigazete.gov.tr/eskiler/2025/12/20251231M6-12.pdf",
      "https://www.resmigazete.gov.tr/eskiler/2025/12/20251231M6-13.pdf",
      "https://www.resmigazete.gov.tr/eskiler/2025/12/20251231M6-14.pdf"
    ],
    "content_hash": "f8791969d8bcdbdaa443dfeba123de17988ee4307bdf51ff911b39c740313942",
    "text_len": 4299,
    "agent_id": "bc001",
    "project_id": 6
  },
  {
    "page_id": "4932112a8591c3fb3b013599d464c82fab1dea5d",
    "job_id": "22b02a9a-e239-4e6f-9519-a7f6b6bdd8a0",
    "url": "https://www.resmigazete.gov.tr/eskiler/2026/01/20260109-1.htm",
    "domain": "resmigazete.gov.tr",
    "depth": 1,
    "text_path": "data/resmigazete_gov_tr/pages/text/4932112a8591c3fb3b013599d464c82fab1dea5d.txt",
    "content_type": "text/html",
    "discovered_links": [],
    "discovered_files": [
      "https://www.resmigazete.gov.tr/eskiler/2026/01/20260109-1-1.pdf"
    ],
    "content_hash": "02957340ca8a0ee0b58074f9ce28f29d931a8f4b008e5d47f58b9db8c73522ed",
    "text_len": 63366,
    "agent_id": "bc001",
    "project_id": 6
  },
  {
    "page_id": "3cf5338d40aab8160b15f83862480bf84b8e17c8",
    "job_id": "22b02a9a-e239-4e6f-9519-a7f6b6bdd8a0",
    "url": "https://resmigazete.gov.tr/08.01.2026",
    "domain": "resmigazete.gov.tr",
    "depth": 1,
    "text_path": "data/resmigazete_gov_tr/pages/text/3cf5338d40aab8160b15f83862480bf84b8e17c8.txt",
    "content_type": "text/html; charset=utf-8",
    "discovered_links": [
      "https://resmigazete.gov.tr/",
      "https://resmigazete.gov.tr/08.01.2026",
      "https://resmigazete.gov.tr/fihrist?tarih=2025-12-31&mukerrer=6",
      "https://resmigazete.gov.tr/07.01.2026",
      "https://resmigazete.gov.tr/09.01.2026",
      "https://www.resmigazete.gov.tr/eskiler/2026/01/20260108-13.htm",
      "https://www.resmigazete.gov.tr/eskiler/2026/01/20260108-14.htm",
      "https://www.resmigazete.gov.tr/eskiler/2026/01/20260108-15.htm",
      "https://www.resmigazete.gov.tr/eskiler/2026/01/20260108-16.htm",
      "https://www.resmigazete.gov.tr/eskiler/2026/01/20260108-17.htm",
      "https://www.resmigazete.gov.tr/eskiler/2026/01/20260108-18.htm",
      "https://www.resmigazete.gov.tr/eskiler/2026/01/20260108-19.htm",
      "https://www.resmigazete.gov.tr/ilanlar/eskiilanlar/2026/01/20260108-2.htm",
      "https://www.resmigazete.gov.tr/ilanlar/eskiilanlar/2026/01/20260108-3.htm",
      "https://www.resmigazete.gov.tr/ilanlar/eskiilanlar/2026/01/20260108-4.htm",
      "https://www.resmigazete.gov.tr/ilanlar/eskiilanlar/2026/01/20260108-5.htm"
    ],
    "discovered_files": [
      "https://www.resmigazete.gov.tr/eskiler/2026/01/20260108.pdf",
      "https://www.resmigazete.gov.tr/eskiler/2026/01/20260108-1.pdf",
      "https://www.resmigazete.gov.tr/eskiler/2026/01/20260108-2.pdf",
      "https://www.resmigazete.gov.tr/eskiler/2026/01/20260108-3.pdf",
      "https://www.resmigazete.gov.tr/eskiler/2026/01/20260108-4.pdf",
      "https://www.resmigazete.gov.tr/eskiler/2026/01/20260108-5.pdf",
      "https://www.resmigazete.gov.tr/eskiler/2026/01/20260108-6.pdf",
      "https://www.resmigazete.gov.tr/eskiler/2026/01/20260108-7.pdf",
      "https://www.resmigazete.gov.tr/eskiler/2026/01/20260108-8.pdf",
      "https://www.resmigazete.gov.tr/eskiler/2026/01/20260108-9.pdf",
      "https://www.resmigazete.gov.tr/eskiler/2026/01/20260108-10.pdf",
      "https://www.resmigazete.gov.tr/eskiler/2026/01/20260108-11.pdf",
      "https://www.resmigazete.gov.tr/eskiler/2026/01/20260108-12.pdf",
      "https://www.resmigazete.gov.tr/eskiler/2026/01/20260108-20.pdf",
      "https://www.resmigazete.gov.tr/eskiler/2026/01/20260108-21.pdf"
    ],
    "content_hash": "db1478324cc086fa4fa9302cacdc4b66244e8fda29a11f8b0d69113cb3b77546",
    "text_len": 45241,
    "agent_id": "bc001",
    "project_id": 6
  },
  {
    "page_id": "7951c7451f88956e8ef969f57209d874e4ec6de0",
    "job_id": "22b02a9a-e239-4e6f-9519-a7f6b6bdd8a0",
    "url": "https://www.resmigazete.gov.tr/eskiler/2026/01/20260109-2.htm",
    "domain": "resmigazete.gov.tr",
    "depth": 1,
    "text_path": "data/resmigazete_gov_tr/pages/text/7951c7451f88956e8ef969f57209d874e4ec6de0.txt",
    "content_type": "text/html",
    "discovered_links": [],
    "discovered_files": [],
    "content_hash": "51970ef0cb63309a4f8ef7223d9771ed975553375c398e68c6835b9d33cec2ca",
    "text_len": 1270,
    "agent_id": "bc001",
    "project_id": 6
  },
  {
    "page_id": "664e8e1f253a05237e3ba6a5aa0367491009b2d4",
    "job_id": "22b02a9a-e239-4e6f-9519-a7f6b6bdd8a0",
    "url": "https://www.resmigazete.gov.tr/eskiler/2026/01/20260109-4.htm",
    "domain": "resmigazete.gov.tr",
    "depth": 1,
    "text_path": "data/resmigazete_gov_tr/pages/text/664e8e1f253a05237e3ba6a5aa0367491009b2d4.txt",
    "content_type": "text/html",
    "discovered_links": [],
    "discovered_files": [],
    "content_hash": "848c147d974862e7e8161164009c6ee07f1f84cbe14be7e7f332f4cf2231919f",
    "text_len": 9426,
    "agent_id": "bc001",
    "project_id": 6
  },
  {
    "page_id": "bafce85d5f6c83af5c946541bae162df2040ead8",
    "job_id": "22b02a9a-e239-4e6f-9519-a7f6b6bdd8a0",
    "url": "https://www.resmigazete.gov.tr/eskiler/2026/01/20260109-5.htm",
    "domain": "resmigazete.gov.tr",
    "depth": 1,
    "text_path": "data/resmigazete_gov_tr/pages/text/bafce85d5f6c83af5c946541bae162df2040ead8.txt",
    "content_type": "text/html",
    "discovered_links": [],
    "discovered_files": [
      "https://www.resmigazete.gov.tr/eskiler/2026/01/20260109-5-1.pdf"
    ],
    "content_hash": "f19b0012d932228af7139ad4474ab461417dd1005b473052202d8fb4ea697dd9",
    "text_len": 1168,
    "agent_id": "bc001",
    "project_id": 6
  },
  {
    "page_id": "9dccd5b91eb6de37c4cac15fc5cbb8e7c5c08493",
    "job_id": "22b02a9a-e239-4e6f-9519-a7f6b6bdd8a0",
    "url": "https://www.resmigazete.gov.tr/ilanlar/eskiilanlar/2026/01/20260109-2.htm",
    "domain": "resmigazete.gov.tr",
    "depth": 1,
    "text_path": "data/resmigazete_gov_tr/pages/text/9dccd5b91eb6de37c4cac15fc5cbb8e7c5c08493.txt",
    "content_type": "text/html",
    "discovered_links": [],
    "discovered_files": [
      "https://www.resmigazete.gov.tr/ilanlar/eskiilanlar/2026/01/20260109-2-1.pdf",
      "https://www.resmigazete.gov.tr/ilanlar/eskiilanlar/2026/01/20260109-2-2.pdf",
      "https://www.resmigazete.gov.tr/ilanlar/eskiilanlar/2026/01/20260109-2-3.pdf",
      "https://www.resmigazete.gov.tr/ilanlar/eskiilanlar/2026/01/20260109-2-4.pdf"
    ],
    "content_hash": "3113bab65882ace26d6a8722f2d3ed9dd19ce49d3e251b8ef59e58d1fbc8eea7",
    "text_len": 247,
    "agent_id": "bc001",
    "project_id": 6
  },
  {
    "page_id": "e404cb0220bad67ea1b9aa9397bbd05d525fd1a5",
    "job_id": "22b02a9a-e239-4e6f-9519-a7f6b6bdd8a0",
    "url": "https://www.resmigazete.gov.tr/eskiler/2026/01/20260109-3.htm",
    "domain": "resmigazete.gov.tr",
    "depth": 1,
    "text_path": "data/resmigazete_gov_tr/pages/text/e404cb0220bad67ea1b9aa9397bbd05d525fd1a5.txt",
    "content_type": "text/html",
    "discovered_links": [],
    "discovered_files": [],
    "content_hash": "b12b6d1aeebc419f6f769c102815bbd68ad19f9dafcb0bf75982fec0b0a0e6e6",
    "text_len": 10731,
    "agent_id": "bc001",
    "project_id": 6
  },
  {
    "page_id": "063e7bc1f9232afdcdb82039eeb281c53b802c5a",
    "job_id": "22b02a9a-e239-4e6f-9519-a7f6b6bdd8a0",
    "url": "https://www.resmigazete.gov.tr/ilanlar/eskiilanlar/2026/01/20260109-3.htm",
    "domain": "resmigazete.gov.tr",
    "depth": 1,
    "text_path": "data/resmigazete_gov_tr/pages/text/063e7bc1f9232afdcdb82039eeb281c53b802c5a.txt",
    "content_type": "text/html",
    "discovered_links": [],
    "discovered_files": [
      "https://www.resmigazete.gov.tr/ilanlar/eskiilanlar/2026/01/20260109-3-1.pdf",
      "https://www.resmigazete.gov.tr/ilanlar/eskiilanlar/2026/01/20260109-3-2.pdf",
      "https://www.resmigazete.gov.tr/ilanlar/eskiilanlar/2026/01/20260109-3-3.pdf",
      "https://www.resmigazete.gov.tr/ilanlar/eskiilanlar/2026/01/20260109-3-4.pdf",
      "https://www.resmigazete.gov.tr/ilanlar/eskiilanlar/2026/01/20260109-3-5.pdf",
      "https://www.resmigazete.gov.tr/ilanlar/eskiilanlar/2026/01/20260109-3-6.pdf"
    ],
    "content_hash": "4a1d330517fbb0b77ea9ef35053eb05646b607306799f0387164580f0e63f6f8",
    "text_len": 673,
    "agent_id": "bc001",
    "project_id": 6
  },
  {
    "page_id": "60bf051aedfd6c16deaded6c67eeaadb4aeca9f5",
    "job_id": "22b02a9a-e239-4e6f-9519-a7f6b6bdd8a0",
    "url": "https://www.resmigazete.gov.tr/ilanlar/eskiilanlar/2026/01/20260109-4.htm",
    "domain": "resmigazete.gov.tr",
    "depth": 1,
    "text_path": "data/resmigazete_gov_tr/pages/text/60bf051aedfd6c16deaded6c67eeaadb4aeca9f5.txt",
    "content_type": "text/html",
    "discovered_links": [],
    "discovered_files": [
      "https://www.resmigazete.gov.tr/ilanlar/eskiilanlar/2026/01/20260109-4-1.pdf",
      "https://www.resmigazete.gov.tr/ilanlar/eskiilanlar/2026/01/20260109-4-2.pdf",
      "https://www.resmigazete.gov.tr/ilanlar/eskiilanlar/2026/01/20260109-4-3.pdf",
      "https://www.resmigazete.gov.tr/ilanlar/eskiilanlar/2026/01/20260109-4-4.pdf",
      "https://www.resmigazete.gov.tr/ilanlar/eskiilanlar/2026/01/20260109-4-5.pdf",
      "https://www.resmigazete.gov.tr/ilanlar/eskiilanlar/2026/01/20260109-4-6.pdf",
      "https://www.resmigazete.gov.tr/ilanlar/eskiilanlar/2026/01/20260109-4-7.pdf",
      "https://www.resmigazete.gov.tr/ilanlar/eskiilanlar/2026/01/20260109-4-8.pdf",
      "https://www.resmigazete.gov.tr/ilanlar/eskiilanlar/2026/01/20260109-4-9.pdf",
      "https://www.resmigazete.gov.tr/ilanlar/eskiilanlar/2026/01/20260109-4-10.pdf",
      "https://www.resmigazete.gov.tr/ilanlar/eskiilanlar/2026/01/20260109-4-11.pdf",
      "https://www.resmigazete.gov.tr/ilanlar/eskiilanlar/2026/01/20260109-4-12.pdf",
      "https://www.resmigazete.gov.tr/ilanlar/eskiilanlar/2026/01/20260109-4-13.pdf",
      "https://www.resmigazete.gov.tr/ilanlar/eskiilanlar/2026/01/20260109-4-14.pdf",
      "https://www.resmigazete.gov.tr/ilanlar/eskiilanlar/2026/01/20260109-4-15.pdf",
      "https://www.resmigazete.gov.tr/ilanlar/eskiilanlar/2026/01/20260109-4-16.pdf",
      "https://www.resmigazete.gov.tr/ilanlar/eskiilanlar/2026/01/20260109-4-17.pdf",
      "https://www.resmigazete.gov.tr/ilanlar/eskiilanlar/2026/01/20260109-4-18.pdf",
      "https://www.resmigazete.gov.tr/ilanlar/eskiilanlar/2026/01/20260109-4-19.pdf"
    ],
    "content_hash": "1df42f2769bf8ce17b28c8ca031e8f8f5dce2ec174e702495bc64e6280121a03",
    "text_len": 974,
    "agent_id": "bc001",
    "project_id": 6
  },
  {
    "page_id": "cff354b9fb906a5d65c34daceab3a817bf51b16d",
    "job_id": "22b02a9a-e239-4e6f-9519-a7f6b6bdd8a0",
    "url": "https://www.resmigazete.gov.tr/ilanlar/eskiilanlar/2026/01/20260109-5.htm",
    "domain": "resmigazete.gov.tr",
    "depth": 1,
    "text_path": "data/resmigazete_gov_tr/pages/text/cff354b9fb906a5d65c34daceab3a817bf51b16d.txt",
    "content_type": "text/html",
    "discovered_links": [
      "https://www.resmigazete.gov.tr/ilanlar/eskiilanlar/2026/01/20260109-5.htm"
    ],
    "discovered_files": [],
    "content_hash": "606e19fbc9429342509f561c73ba3279ad7dd1341f846fbd06a97c0666433cfd",
    "text_len": 76,
    "agent_id": "bc001",
    "project_id": 6
  },
  {
    "page_id": "c62d0301256d024a8b7a4d6992c024598d01a4fe",
    "job_id": "22b02a9a-e239-4e6f-9519-a7f6b6bdd8a0",
    "url": "https://resmigazete.gov.tr/07.01.2026",
    "domain": "resmigazete.gov.tr",
    "depth": 2,
    "text_path": "data/resmigazete_gov_tr/pages/text/c62d0301256d024a8b7a4d6992c024598d01a4fe.txt",
    "content_type": "text/html; charset=utf-8",
    "discovered_links": [
      "https://resmigazete.gov.tr/",
      "https://resmigazete.gov.tr/07.01.2026",
      "https://resmigazete.gov.tr/fihrist?tarih=2025-12-31&mukerrer=6",
      "https://resmigazete.gov.tr/06.01.2026",
      "https://resmigazete.gov.tr/08.01.2026",
      "https://www.resmigazete.gov.tr/eskiler/2026/01/20260107-5.htm",
      "https://www.resmigazete.gov.tr/eskiler/2026/01/20260107-6.htm",
      "https://www.resmigazete.gov.tr/eskiler/2026/01/20260107-7.htm",
      "https://www.resmigazete.gov.tr/eskiler/2026/01/20260107-8.htm",
      "https://www.resmigazete.gov.tr/eskiler/2026/01/20260107-9.htm",
      "https://www.resmigazete.gov.tr/ilanlar/eskiilanlar/2026/01/20260107-3.htm",
      "https://www.resmigazete.gov.tr/ilanlar/eskiilanlar/2026/01/20260107-4.htm",
      "https://www.resmigazete.gov.tr/ilanlar/eskiilanlar/2026/01/20260107-5.htm"
    ],
    "discovered_files": [
      "https://www.resmigazete.gov.tr/eskiler/2026/01/20260107.pdf",
      "https://www.resmigazete.gov.tr/eskiler/2026/01/20260107-1.pdf",
      "https://www.resmigazete.gov.tr/eskiler/2026/01/20260107-2.pdf",
      "https://www.resmigazete.gov.tr/eskiler/2026/01/20260107-3.pdf",
      "https://www.resmigazete.gov.tr/eskiler/2026/01/20260107-4.pdf",
      "https://www.resmigazete.gov.tr/eskiler/2026/01/20260107-10.pdf"
    ],
    "content_hash": "25ae363b614d543e7d80d3704e3ecdf2ae8b6394f14b01bf29a897ff52c46a65",
    "text_len": 42458,
    "agent_id": "bc001",
    "project_id": 6
  },
  {
    "page_id": "288d90152500d0ad27b5051d3dcffe95a5b356fb",
    "job_id": "22b02a9a-e239-4e6f-9519-a7f6b6bdd8a0",
    "url": "https://resmigazete.gov.tr/09.01.2026",
    "domain": "resmigazete.gov.tr",
    "depth": 2,
    "text_path": "data/resmigazete_gov_tr/pages/text/288d90152500d0ad27b5051d3dcffe95a5b356fb.txt",
    "content_type": "text/html; charset=utf-8",
    "discovered_links": [
      "https://resmigazete.gov.tr/",
      "https://resmigazete.gov.tr/09.01.2026",
      "https://resmigazete.gov.tr/fihrist?tarih=2025-12-31&mukerrer=6",
      "https://resmigazete.gov.tr/08.01.2026",
      "https://www.resmigazete.gov.tr/eskiler/2026/01/20260109-1.htm",
      "https://www.resmigazete.gov.tr/eskiler/2026/01/20260109-2.htm",
      "https://www.resmigazete.gov.tr/eskiler/2026/01/20260109-3.htm",
      "https://www.resmigazete.gov.tr/eskiler/2026/01/20260109-4.htm",
      "https://www.resmigazete.gov.tr/eskiler/2026/01/20260109-5.htm",
      "https://www.resmigazete.gov.tr/ilanlar/eskiilanlar/2026/01/20260109-2.htm",
      "https://www.resmigazete.gov.tr/ilanlar/eskiilanlar/2026/01/20260109-3.htm",
      "https://www.resmigazete.gov.tr/ilanlar/eskiilanlar/2026/01/20260109-4.htm",
      "https://www.resmigazete.gov.tr/ilanlar/eskiilanlar/2026/01/20260109-5.htm"
    ],
    "discovered_files": [
      "https://www.resmigazete.gov.tr/eskiler/2026/01/20260109.pdf",
      "https://www.resmigazete.gov.tr/eskiler/2026/01/20260109-6.pdf",
      "https://www.resmigazete.gov.tr/eskiler/2026/01/20260109-7.pdf"
    ],
    "content_hash": "61f7d67a03e57a3acc059f3139a296866cd45cfe5f43cd75d92c7561e0dc499d",
    "text_len": 41802,
    "agent_id": "bc001",
    "project_id": 6
  },
  {
    "page_id": "1e7ff78bfd597e25a0a0f94addeb2816ded20e27",
    "job_id": "22b02a9a-e239-4e6f-9519-a7f6b6bdd8a0",
    "url": "https://www.resmigazete.gov.tr/eskiler/2026/01/20260108-13.htm",
    "domain": "resmigazete.gov.tr",
    "depth": 2,
    "text_path": "data/resmigazete_gov_tr/pages/text/1e7ff78bfd597e25a0a0f94addeb2816ded20e27.txt",
    "content_type": "text/html",
    "discovered_links": [],
    "discovered_files": [],
    "content_hash": "88b3cc21b81f62d477fb250592e47983b50acb55993297ee972151e2f45abfc9",
    "text_len": 667,
    "agent_id": "bc001",
    "project_id": 6
  },
  {
    "page_id": "413c47816e9df7bab656e9d3e107a1229192db3e",
    "job_id": "22b02a9a-e239-4e6f-9519-a7f6b6bdd8a0",
    "url": "https://www.resmigazete.gov.tr/eskiler/2026/01/20260108-14.htm",
    "domain": "resmigazete.gov.tr",
    "depth": 2,
    "text_path": "data/resmigazete_gov_tr/pages/text/413c47816e9df7bab656e9d3e107a1229192db3e.txt",
    "content_type": "text/html",
    "discovered_links": [],
    "discovered_files": [],
    "content_hash": "50abf5f736930b3066d466d0fec0a701ec4bcdc3b1c78f64b7c580e5a2bf30e2",
    "text_len": 58499,
    "agent_id": "bc001",
    "project_id": 6
  },
  {
    "page_id": "95c04f9c9ec26e60bbdef33d3141eae54e16fd0e",
    "job_id": "22b02a9a-e239-4e6f-9519-a7f6b6bdd8a0",
    "url": "https://www.resmigazete.gov.tr/eskiler/2026/01/20260108-15.htm",
    "domain": "resmigazete.gov.tr",
    "depth": 2,
    "text_path": "data/resmigazete_gov_tr/pages/text/95c04f9c9ec26e60bbdef33d3141eae54e16fd0e.txt",
    "content_type": "text/html",
    "discovered_links": [],
    "discovered_files": [],
    "content_hash": "3830158e2ca6dee4592d3890f7cc0c96aab216966a72692b21d9c039bc4b89a9",
    "text_len": 11071,
    "agent_id": "bc001",
    "project_id": 6
  },
  {
    "page_id": "59b25220f46f1858e4129e389b61807265a84efc",
    "job_id": "22b02a9a-e239-4e6f-9519-a7f6b6bdd8a0",
    "url": "https://www.resmigazete.gov.tr/eskiler/2026/01/20260108-17.htm",
    "domain": "resmigazete.gov.tr",
    "depth": 2,
    "text_path": "data/resmigazete_gov_tr/pages/text/59b25220f46f1858e4129e389b61807265a84efc.txt",
    "content_type": "text/html",
    "discovered_links": [],
    "discovered_files": [],
    "content_hash": "d45ed0635663379af09014ab6f6eebbbf34d3e97691df21d975d6ad787a43f97",
    "text_len": 1875,
    "agent_id": "bc001",
    "project_id": 6
  },
  {
    "page_id": "432e544c0aafc18ff23b09b7a858abb78288c4ee",
    "job_id": "22b02a9a-e239-4e6f-9519-a7f6b6bdd8a0",
    "url": "https://www.resmigazete.gov.tr/eskiler/2026/01/20260108-16.htm",
    "domain": "resmigazete.gov.tr",
    "depth": 2,
    "text_path": "data/resmigazete_gov_tr/pages/text/432e544c0aafc18ff23b09b7a858abb78288c4ee.txt",
    "content_type": "text/html",
    "discovered_links": [],
    "discovered_files": [],
    "content_hash": "b62f4ee61e8fc823a11f5ba3c785906e966ab5287c64c5994ed1adb887e1c75a",
    "text_len": 9667,
    "agent_id": "bc001",
    "project_id": 6
  },
  {
    "page_id": "5077529cea41f60fdd8f2eb3f528b541cb6cf7df",
    "job_id": "22b02a9a-e239-4e6f-9519-a7f6b6bdd8a0",
    "url": "https://www.resmigazete.gov.tr/eskiler/2026/01/20260108-19.htm",
    "domain": "resmigazete.gov.tr",
    "depth": 2,
    "text_path": "data/resmigazete_gov_tr/pages/text/5077529cea41f60fdd8f2eb3f528b541cb6cf7df.txt",
    "content_type": "text/html",
    "discovered_links": [],
    "discovered_files": [],
    "content_hash": "71b94be1d43a41f3a8a3c2190a17346d62752039648bb1fe2b8fd24f483dbb77",
    "text_len": 424,
    "agent_id": "bc001",
    "project_id": 6
  },
  {
    "page_id": "2e6f0818926e9046a7f285c0d634ea37b7f61789",
    "job_id": "22b02a9a-e239-4e6f-9519-a7f6b6bdd8a0",
    "url": "https://www.resmigazete.gov.tr/eskiler/2026/01/20260108-18.htm",
    "domain": "resmigazete.gov.tr",
    "depth": 2,
    "text_path": "data/resmigazete_gov_tr/pages/text/2e6f0818926e9046a7f285c0d634ea37b7f61789.txt",
    "content_type": "text/html",
    "discovered_links": [],
    "discovered_files": [],
    "content_hash": "bcaeebd1094835bab8233afc5420fadb6d763fc55dceaf3a2164665ca02340b4",
    "text_len": 879,
    "agent_id": "bc001",
    "project_id": 6
  },
  {
    "page_id": "3ccfb962280747f7599270ff65d9f822e8f9f4f8",
    "job_id": "22b02a9a-e239-4e6f-9519-a7f6b6bdd8a0",
    "url": "https://www.resmigazete.gov.tr/ilanlar/eskiilanlar/2026/01/20260108-2.htm",
    "domain": "resmigazete.gov.tr",
    "depth": 2,
    "text_path": "data/resmigazete_gov_tr/pages/text/3ccfb962280747f7599270ff65d9f822e8f9f4f8.txt",
    "content_type": "text/html",
    "discovered_links": [],
    "discovered_files": [
      "https://www.resmigazete.gov.tr/ilanlar/eskiilanlar/2026/01/20260108-2-1.pdf",
      "https://www.resmigazete.gov.tr/ilanlar/eskiilanlar/2026/01/20260108-2-2.pdf"
    ],
    "content_hash": "d3c47e194a090b9be46e4917fed67e047df8c166499e8ef33f19475f24097f5b",
    "text_len": 147,
    "agent_id": "bc001",
    "project_id": 6
  },
  {
    "page_id": "7919057f15b4dc03584559b14e564869d3f2c768",
    "job_id": "22b02a9a-e239-4e6f-9519-a7f6b6bdd8a0",
    "url": "https://www.resmigazete.gov.tr/ilanlar/eskiilanlar/2026/01/20260108-3.htm",
    "domain": "resmigazete.gov.tr",
    "depth": 2,
    "text_path": "data/resmigazete_gov_tr/pages/text/7919057f15b4dc03584559b14e564869d3f2c768.txt",
    "content_type": "text/html",
    "discovered_links": [],
    "discovered_files": [
      "https://www.resmigazete.gov.tr/ilanlar/eskiilanlar/2026/01/20260108-3-1.pdf",
      "https://www.resmigazete.gov.tr/ilanlar/eskiilanlar/2026/01/20260108-3-2.pdf",
      "https://www.resmigazete.gov.tr/ilanlar/eskiilanlar/2026/01/20260108-3-3.pdf",
      "https://www.resmigazete.gov.tr/ilanlar/eskiilanlar/2026/01/20260108-3-4.pdf"
    ],
    "content_hash": "04b79dfb0e1169a0a70f83f777432da6aae4959112ee3638dd362f8636c9bd7a",
    "text_len": 487,
    "agent_id": "bc001",
    "project_id": 6
  },
  {
    "page_id": "a6f9f898da68627c07f4763714f936b6b9f6bb9a",
    "job_id": "22b02a9a-e239-4e6f-9519-a7f6b6bdd8a0",
    "url": "https://www.resmigazete.gov.tr/ilanlar/eskiilanlar/2026/01/20260108-4.htm",
    "domain": "resmigazete.gov.tr",
    "depth": 2,
    "text_path": "data/resmigazete_gov_tr/pages/text/a6f9f898da68627c07f4763714f936b6b9f6bb9a.txt",
    "content_type": "text/html",
    "discovered_links": [],
    "discovered_files": [
      "https://www.resmigazete.gov.tr/ilanlar/eskiilanlar/2026/01/20260108-4-1.pdf",
      "https://www.resmigazete.gov.tr/ilanlar/eskiilanlar/2026/01/20260108-4-2.pdf",
      "https://www.resmigazete.gov.tr/ilanlar/eskiilanlar/2026/01/20260108-4-3.pdf",
      "https://www.resmigazete.gov.tr/ilanlar/eskiilanlar/2026/01/20260108-4-4.pdf",
      "https://www.resmigazete.gov.tr/ilanlar/eskiilanlar/2026/01/20260108-4-5.pdf",
      "https://www.resmigazete.gov.tr/ilanlar/eskiilanlar/2026/01/20260108-4-6.pdf",
      "https://www.resmigazete.gov.tr/ilanlar/eskiilanlar/2026/01/20260108-4-7.pdf",
      "https://www.resmigazete.gov.tr/ilanlar/eskiilanlar/2026/01/20260108-4-8.pdf",
      "https://www.resmigazete.gov.tr/ilanlar/eskiilanlar/2026/01/20260108-4-9.pdf",
      "https://www.resmigazete.gov.tr/ilanlar/eskiilanlar/2026/01/20260108-4-10.pdf",
      "https://www.resmigazete.gov.tr/ilanlar/eskiilanlar/2026/01/20260108-4-11.pdf"
    ],
    "content_hash": "597c138d4188d0ae114f66aacdc5b00bee52ef67b8786e6310e51629f8f9c5b5",
    "text_len": 603,
    "agent_id": "bc001",
    "project_id": 6
  },
  {
    "page_id": "e7043eb79071ff4355339f129a219656f3935e75",
    "job_id": "22b02a9a-e239-4e6f-9519-a7f6b6bdd8a0",
    "url": "https://www.resmigazete.gov.tr/ilanlar/eskiilanlar/2026/01/20260108-5.htm",
    "domain": "resmigazete.gov.tr",
    "depth": 2,
    "text_path": "data/resmigazete_gov_tr/pages/text/e7043eb79071ff4355339f129a219656f3935e75.txt",
    "content_type": "text/html",
    "discovered_links": [
      "https://www.resmigazete.gov.tr/ilanlar/eskiilanlar/2026/01/20260108-5.htm"
    ],
    "discovered_files": [],
    "content_hash": "8350d13d62e2d2782fda6dc51c1e09f3d3a3081a79d9d2e9f474522e36cd0590",
    "text_len": 80,
    "agent_id": "bc001",
    "project_id": 6
  },
  {
    "page_id": "c37fd3a3e9057a24da68e3a664ccb3b88e12cd18",
    "job_id": "22b02a9a-e239-4e6f-9519-a7f6b6bdd8a0",
    "url": "https://www.resmigazete.gov.tr/ilanlar/eskiilanlar/2025/12/20251231%20M6-4.htm",
    "domain": "resmigazete.gov.tr",
    "depth": 2,
    "text_path": "data/resmigazete_gov_tr/pages/text/c37fd3a3e9057a24da68e3a664ccb3b88e12cd18.txt",
    "content_type": "text/html",
    "discovered_links": [],
    "discovered_files": [
      "https://www.resmigazete.gov.tr/ilanlar/eskiilanlar/2025/12/20251231M6-4-1.pdf",
      "https://www.resmigazete.gov.tr/ilanlar/eskiilanlar/2025/12/20251231M6-4-2.pdf",
      "https://www.resmigazete.gov.tr/ilanlar/eskiilanlar/2025/12/20251231M6-4-3.pdf",
      "https://www.resmigazete.gov.tr/ilanlar/eskiilanlar/2025/12/20251231M6-4-4.pdf",
      "https://www.resmigazete.gov.tr/ilanlar/eskiilanlar/2025/12/20251231M6-4-5.pdf",
      "https://www.resmigazete.gov.tr/ilanlar/eskiilanlar/2025/12/20251231M6-4-6.pdf",
      "https://www.resmigazete.gov.tr/ilanlar/eskiilanlar/2025/12/20251231M6-4-7.pdf",
      "https://www.resmigazete.gov.tr/ilanlar/eskiilanlar/2025/12/20251231M6-4-8.pdf",
      "https://www.resmigazete.gov.tr/ilanlar/eskiilanlar/2025/12/20251231M6-4-21.pdf",
      "https://www.resmigazete.gov.tr/ilanlar/eskiilanlar/2025/12/20251231M6-4-22.pdf",
      "https://www.resmigazete.gov.tr/ilanlar/eskiilanlar/2025/12/20251231M6-4-9.pdf",
      "https://www.resmigazete.gov.tr/ilanlar/eskiilanlar/2025/12/20251231M6-4-10.pdf",
      "https://www.resmigazete.gov.tr/ilanlar/eskiilanlar/2025/12/20251231M6-4-11.pdf",
      "https://www.resmigazete.gov.tr/ilanlar/eskiilanlar/2025/12/20251231M6-4-12.pdf",
      "https://www.resmigazete.gov.tr/ilanlar/eskiilanlar/2025/12/20251231M6-4-13.pdf",
      "https://www.resmigazete.gov.tr/ilanlar/eskiilanlar/2025/12/20251231M6-4-14.pdf",
      "https://www.resmigazete.gov.tr/ilanlar/eskiilanlar/2025/12/20251231M6-4-15.pdf",
      "https://www.resmigazete.gov.tr/ilanlar/eskiilanlar/2025/12/20251231M6-4-16.pdf",
      "https://www.resmigazete.gov.tr/ilanlar/eskiilanlar/2025/12/20251231M6-4-17.pdf",
      "https://www.resmigazete.gov.tr/ilanlar/eskiilanlar/2025/12/20251231M6-4-18.pdf",
      "https://www.resmigazete.gov.tr/ilanlar/eskiilanlar/2025/12/20251231M6-4-19.pdf",
      "https://www.resmigazete.gov.tr/ilanlar/eskiilanlar/2025/12/20251231M6-4-20.pdf"
    ],
    "content_hash": "fe38a38e6e26123818cc6a538f9aed553acf287a449d17a5cbad0ded1c5a64c1",
    "text_len": 1146,
    "agent_id": "bc001",
    "project_id": 6
  },
  {
    "page_id": "1bb00cbba5a93c21000bacb31a046d1e0b3124af",
    "job_id": "22b02a9a-e239-4e6f-9519-a7f6b6bdd8a0",
    "url": "https://resmigazete.gov.tr/fihrist?tarih=2025-12-31&mukerrer=5",
    "domain": "resmigazete.gov.tr",
    "depth": 2,
    "text_path": "data/resmigazete_gov_tr/pages/text/1bb00cbba5a93c21000bacb31a046d1e0b3124af.txt",
    "content_type": "text/html; charset=utf-8",
    "discovered_links": [
      "https://resmigazete.gov.tr/",
      "https://resmigazete.gov.tr/fihrist?tarih=2025-12-31&mukerrer=4",
      "https://resmigazete.gov.tr/fihrist?tarih=2025-12-31&mukerrer=6",
      "https://resmigazete.gov.tr/fihrist?tarih=2025-12-31&mukerrer=5"
    ],
    "discovered_files": [
      "https://www.resmigazete.gov.tr/eskiler/2025/12/20251231M5.pdf",
      "https://www.resmigazete.gov.tr/eskiler/2025/12/20251231M5-1.pdf",
      "https://www.resmigazete.gov.tr/eskiler/2025/12/20251231M5-2.pdf",
      "https://www.resmigazete.gov.tr/eskiler/2025/12/20251231M5-3.pdf",
      "https://www.resmigazete.gov.tr/eskiler/2025/12/20251231M5-4.pdf",
      "https://www.resmigazete.gov.tr/eskiler/2025/12/20251231M5-5.pdf",
      "https://www.resmigazete.gov.tr/eskiler/2025/12/20251231M5-6.pdf",
      "https://www.resmigazete.gov.tr/eskiler/2025/12/20251231M5-7.pdf",
      "https://www.resmigazete.gov.tr/eskiler/2025/12/20251231M5-8.pdf",
      "https://www.resmigazete.gov.tr/eskiler/2025/12/20251231M5-9.pdf",
      "https://www.resmigazete.gov.tr/eskiler/2025/12/20251231M5-10.pdf",
      "https://www.resmigazete.gov.tr/eskiler/2025/12/20251231M5-11.pdf",
      "https://www.resmigazete.gov.tr/eskiler/2025/12/20251231M5-12.pdf",
      "https://www.resmigazete.gov.tr/eskiler/2025/12/20251231M5-13.pdf",
      "https://www.resmigazete.gov.tr/eskiler/2025/12/20251231M5-14.pdf",
      "https://www.resmigazete.gov.tr/eskiler/2025/12/20251231M5-15.pdf",
      "https://www.resmigazete.gov.tr/eskiler/2025/12/20251231M5-16.pdf",
      "https://www.resmigazete.gov.tr/eskiler/2025/12/20251231M5-17.pdf",
      "https://www.resmigazete.gov.tr/eskiler/2025/12/20251231M5-18.pdf",
      "https://www.resmigazete.gov.tr/eskiler/2025/12/20251231M5-19.pdf",
      "https://www.resmigazete.gov.tr/eskiler/2025/12/20251231M5-21.pdf",
      "https://www.resmigazete.gov.tr/eskiler/2025/12/20251231M5-20.pdf",
      "https://www.resmigazete.gov.tr/eskiler/2025/12/20251231M5-22.pdf",
      "https://www.resmigazete.gov.tr/eskiler/2025/12/20251231M5-23.pdf",
      "https://www.resmigazete.gov.tr/eskiler/2025/12/20251231M5-24.pdf",
      "https://www.resmigazete.gov.tr/eskiler/2025/12/20251231M5-25.pdf",
      "https://www.resmigazete.gov.tr/eskiler/2025/12/20251231M5-26.pdf",
      "https://www.resmigazete.gov.tr/eskiler/2025/12/20251231M5-27.pdf",
      "https://www.resmigazete.gov.tr/eskiler/2025/12/20251231M5-28.pdf",
      "https://www.resmigazete.gov.tr/eskiler/2025/12/20251231M5-29.pdf",
      "https://www.resmigazete.gov.tr/eskiler/2025/12/20251231M5-30.pdf",
      "https://www.resmigazete.gov.tr/eskiler/2025/12/20251231M5-31.pdf",
      "https://www.resmigazete.gov.tr/eskiler/2025/12/20251231M5-32.pdf",
      "https://www.resmigazete.gov.tr/eskiler/2025/12/20251231M5-33.pdf",
      "https://www.resmigazete.gov.tr/eskiler/2025/12/20251231M5-34.pdf",
      "https://www.resmigazete.gov.tr/eskiler/2025/12/20251231M5-35.pdf",
      "https://www.resmigazete.gov.tr/eskiler/2025/12/20251231M5-36.pdf",
      "https://www.resmigazete.gov.tr/eskiler/2025/12/20251231M5-37.pdf",
      "https://www.resmigazete.gov.tr/eskiler/2025/12/20251231M5-38.pdf"
    ],
    "content_hash": "c0542f0ab5d39b0cedd2e6fcef43b78805f8cfc86463be7d49e3f5a203dc5932",
    "text_len": 6794,
    "agent_id": "bc001",
    "project_id": 6
  }
]